__init__.py
market_abm.py
market_abm-0.0.2.dist-info/METADATA
market_abm-0.0.2.dist-info/WHEEL
market_abm-0.0.2.dist-info/top_level.txt
market_abm-0.0.2.dist-info/RECORD
