Metadata-Version: 2.4
Name: market-abm
Version: 0.0.2
Summary: Market Simulation
Author-email: shazri_shahrir <mdshazrishahrir@gmail.com>
License: MIT
Project-URL: Homepage, https://github.com/merbauinstitute/market_abm/
